task3/dualportram.sv
module dualportram #(
    parameter   ADDRESS_WIDTH = 9,
                DATA_WIDTH = 8
)(
    input logic clk,
    input logic wr_enable,
    input logic rd_enable,
    input logic [ADDRESS_WIDTH-1:0] wr_addr,
    input logic [ADDRESS_WIDTH-1:0] rd_addr,
    input logic [DATA_WIDTH-1:0] din,
    output logic [DATA_WIDTH-1:0] dout
);

logic [DATA_WIDTH-1:0] ram_array [2**ADDRESS_WIDTH-1:0];

always_ff @(posedge clk) begin
    if (wr_enable == 1'b1)
        ram_array[wr_addr] <= din;
    if (rd_enable == 1'b1)
        dout <= ram_array[rd_addr];
    
end
endmodule

task3/counter.sv
module counter #(
    parameter WIDTH = 9
)(
// interface signals
input   logic           clk,
input   logic           rst,
input   logic           en,
input   logic[WIDTH-1:0]   incr,
output  logic [WIDTH-1:0] count
);

always_ff @ (posedge clk)
    if (rst) count <= {WIDTH{1'b0}};
    else if (en) count <= count + incr;




endmodule

task3/sigdelay.sv
module sigdelay #(
        parameter A_WIDTH = 9,
                  D_WIDTH = 8
) (
    input logic        clk,
    input logic        rst,
    input logic        en,
    input logic        wr_enable,
    input logic        rd_enable,
    input logic [D_WIDTH-1:0] din,
    input logic [A_WIDTH-1:0] incr,
    input logic [D_WIDTH-1:0] phase_offset,
    output logic [D_WIDTH-1:0] dout,

);

    logic [A_WIDTH-1:0] address;

counter addrCounter(
    .clk (clk),
    .rst (rst),
    .en (en),
    .incr (incr),
    .count (address1)
);

    assign address2 = address1 + phase_offset;

dualportram sigRam(
    .clk (clk),
    .wr_addr (address2),
    .rd_addr (address1),
    .dout (dout),
    .din (din),
    .wr_enable(wr_enable),
    .rd_enable(rd_enable)
);

endmodule

task3/sigdelay.vcd
$version Generated by VerilatedVcd $end
$date Fri Oct 25 12:32:16 2024 $end
$timescale 1ps $end

 $scope module TOP $end
  $var wire  1 & clk $end
  $var wire  8 + din [7:0] $end
  $var wire  8 . dout [7:0] $end
  $var wire  1 ( en $end
  $var wire  9 , incr [8:0] $end
  $var wire  8 - phase_offset [7:0] $end
  $var wire  1 * rd_enable $end
  $var wire  1 ' rst $end
  $var wire  1 ) wr_enable $end
  $scope module sigdelay $end
   $var wire 32 1 A_WIDTH [31:0] $end
   $var wire 32 2 D_WIDTH [31:0] $end
   $var wire  9 3 address [8:0] $end
   $var wire  1 # address1 $end
   $var wire  1 / address2 $end
   $var wire  1 & clk $end
   $var wire  8 + din [7:0] $end
   $var wire  8 . dout [7:0] $end
   $var wire  1 ( en $end
   $var wire  9 , incr [8:0] $end
   $var wire  8 - phase_offset [7:0] $end
   $var wire  1 * rd_enable $end
   $var wire  1 ' rst $end
   $var wire  1 ) wr_enable $end
   $scope module addrCounter $end
    $var wire 32 1 WIDTH [31:0] $end
    $var wire  1 & clk $end
    $var wire  9 $ count [8:0] $end
    $var wire  1 ( en $end
    $var wire  9 , incr [8:0] $end
    $var wire  1 ' rst $end
   $upscope $end
   $scope module sigRam $end
    $var wire 32 1 ADDRESS_WIDTH [31:0] $end
    $var wire 32 2 DATA_WIDTH [31:0] $end
    $var wire  1 & clk $end
    $var wire  8 + din [7:0] $end
    $var wire  8 . dout [7:0] $end
    $var wire  9 % rd_addr [8:0] $end
    $var wire  1 * rd_enable $end
    $var wire  9 0 wr_addr [8:0] $end
    $var wire  1 ) wr_enable $end
   $upscope $end
  $upscope $end
 $upscope $end
$enddefinitions $end


#0
0#
b000000000 $
b000000000 %
1&
0'
1(
1)
1*
b00000000 +
b000000001 ,
b01000000 -
b00000000 .
0/
b000000000 0
b00000000000000000000000000001001 1
b00000000000000000000000000001000 2
b000000000 3
#1
0&
#2
1#
b000000001 $
b000000001 %
1&
b01100100 +
b00110011 -
#3
0&
#4
0#
b000000010 $
b000000000 %
1&
b01101100 +
1/
b000000001 0
#5
0&
#6
1#
b000000011 $
b000000001 %
1&
b01101111 +
b01100100 .
0/
b000000000 0
#7
0&
#8
0#
b000000100 $
b000000000 %
1&
b01101100 .
1/
b000000001 0
#9
0&
#10
1#
b000000101 $
b000000001 %
1&
b01101011 +
b01101111 .
0/
b000000000 0
#11
0&
#12
0#
b000000110 $
b000000000 %
1&
b01101001 +
1/
b000000001 0
#13
0&
#14
1#
b000000111 $
b000000001 %
1&
b01111010 +
b01101011 .
0/
b000000000 0
#15
0&
#16
0#
b000001000 $
b000000000 %
1&
b01111011 +
b01101001 .
1/
b000000001 0
#17
0&
#18
1#
b000001001 $
b000000001 %
1&
b10000011 +
b01111010 .
0/
b000000000 0
#19
0&
#20
0#
b000001010 $
b000000000 %
1&
b01101101 +
b01111011 .
1/
b000000001 0
#21
0&
#22
1#
b000001011 $
b000000001 %
1&
b01100101 +
b10000011 .
0/
b000000000 0
#23
0&
#24
0#
b000001100 $
b000000000 %
1&
b01011011 +
b01101101 .
1/
b000000001 0
#25
0&
#26
1#
b000001101 $
b000000001 %
1&
b01010100 +
b01100101 .
0/
b000000000 0
#27
0&
#28
0#
b000001110 $
b000000000 %
1&
b01101000 +
b01011011 .
1/
b000000001 0
#29
0&
#30
1#
b000001111 $
b000000001 %
1&
b01101111 +
b01010100 .
0/
b000000000 0
#31
0&
#32
0#
b000010000 $
b000000000 %
1&
b01111001 +
b01101000 .
1/
b000000001 0
#33
0&
#34
1#
b000010001 $
b000000001 %
1&
b10000001 +
b01101111 .
0/
b000000000 0
#35
0&
#36
0#
b000010010 $
b000000000 %
1&
b01110011 +
b01111001 .
1/
b000000001 0
#37
0&
#38
1#
b000010011 $
b000000001 %
1&
b01110110 +
b10000001 .
0/
b000000000 0
#39
0&
#40
0#
b000010100 $
b000000000 %
1&
b10001010 +
b01110011 .
1/
b000000001 0
#41
0&
#42
1#
b000010101 $
b000000001 %
1&
b10000010 +
b01110110 .
0/
b000000000 0
#43
0&
#44
0#
b000010110 $
b000000000 %
1&
b10001010 +
b10001010 .
1/
b000000001 0
#45
0&
#46
1#
b000010111 $
b000000001 %
1&
b10011000 +
b10000010 .
0/
b000000000 0
#47
0&
#48
0#
b000011000 $
b000000000 %
1&
b01101011 +
b10001010 .
1/
b000000001 0
#49
0&
#50
1#
b000011001 $
b000000001 %
1&
b01110101 +
b10011000 .
0/
b000000000 0
#51
0&
#52
0#
b000011010 $
b000000000 %
1&
b01101000 +
b01101011 .
1/
b000000001 0
#53
0&
#54
1#
b000011011 $
b000000001 %
1&
b01110101 .
0/
b000000000 0
#55
0&
#56
0#
b000011100 $
b000000000 %
1&
b10000010 +
b01101000 .
1/
b000000001 0
#57
0&
#58
1#
b000011101 $
b000000001 %
1&
b01111100 +
0/
b000000000 0
#59
0&
#60
0#
b000011110 $
b000000000 %
1&
b10010001 +
b10000010 .
1/
b000000001 0
#61
0&
#62
1#
b000011111 $
b000000001 %
1&
b10000000 +
b01111100 .
0/
b000000000 0
#63
0&
#64
0#
b000100000 $
b000000000 %
1&
b01100010 +
b10010001 .
1/
b000000001 0
#65
0&
#66
1#
b000100001 $
b000000001 %
1&
b01011010 +
b10000000 .
0/
b000000000 0
#67
0&
#68
0#
b000100010 $
b000000000 %
1&
b01001100 +
b01100010 .
1/
b000000001 0
#69
0&
#70
1#
b000100011 $
b000000001 %
1&
b01011110 +
b01011010 .
0/
b000000000 0
#71
0&
#72
0#
b000100100 $
b000000000 %
1&
b01101011 +
b01001100 .
1/
b000000001 0
#73
0&
#74
1#
b000100101 $
b000000001 %
1&
b01101101 +
b01011110 .
0/
b000000000 0
#75
0&
#76
0#
b000100110 $
b000000000 %
1&
b01100100 +
b01101011 .
1/
b000000001 0
#77
0&
#78
1#
b000100111 $
b000000001 %
1&
b01011011 +
b01101101 .
0/
b000000000 0
#79
0&
#80
0#
b000101000 $
b000000000 %
1&
b01001010 +
b01100100 .
1/
b000000001 0
#81
0&
#82
1#
b000101001 $
b000000001 %
1&
b01011011 .
0/
b000000000 0
#83
0&
#84
0#
b000101010 $
b000000000 %
1&
b01101011 +
b01001010 .
1/
b000000001 0
#85
0&
#86
1#
b000101011 $
b000000001 %
1&
b01101110 +
0/
b000000000 0
#87
0&
#88
0#
b000101100 $
b000000000 %
1&
b01111001 +
b01101011 .
1/
b000000001 0
#89
0&
#90
1#
b000101101 $
b000000001 %
1&
b01111101 +
b01101110 .
0/
b000000000 0
#91
0&
#92
0#
b000101110 $
b000000000 %
1&
b01100001 +
b01111001 .
1/
b000000001 0
#93
0&
#94
1#
b000101111 $
b000000001 %
1&
b01100101 +
b01111101 .
0/
b000000000 0
#95
0&
#96
0#
b000110000 $
b000000000 %
1&
b01011011 +
b01100001 .
1/
b000000001 0
#97
0&
#98
1#
b000110001 $
b000000001 %
1&
b01011010 +
b01100101 .
0/
b000000000 0
#99
0&
#100
0#
b000110010 $
b000000000 %
1&
b01110111 +
b01011011 .
1/
b000000001 0
#101
0&
#102
1#
b000110011 $
b000000001 %
1&
b01110100 +
b01011010 .
0/
b000000000 0
#103
0&
#104
0#
b000110100 $
b000000000 %
1&
b01100101 +
b01110111 .
1/
b000000001 0
#105
0&
#106
1#
b000110101 $
b000000001 %
1&
b01010111 +
b01110100 .
0/
b000000000 0
#107
0&
#108
0#
b000110110 $
b000000000 %
1&
b01001000 +
b01100101 .
1/
b000000001 0
#109
0&
#110
1#
b000110111 $
b000000001 %
1&
b01000110 +
b01010111 .
0/
b000000000 0
#111
0&
#112
0#
b000111000 $
b000000000 %
1&
b01010110 +
b01001000 .
1/
b000000001 0
#113
0&
#114
1#
b000111001 $
b000000001 %
1&
b01101100 +
b01000110 .
0/
b000000000 0
#115
0&
#116
0#
b000111010 $
b000000000 %
1&
b01110000 +
b01010110 .
1/
b000000001 0
#117
0&
#118
1#
b000111011 $
b000000001 %
1&
b01111110 +
b01101100 .
0/
b000000000 0
#119
0&
#120
0#
b000111100 $
b000000000 %
1&
b01110000 +
b01110000 .
1/
b000000001 0
#121
0&
#122
1#
b000111101 $
b000000001 %
1&
b01100110 +
b01111110 .
0/
b000000000 0
#123
0&
#124
0#
b000111110 $
b000000000 %
1&
b01101010 +
b01110000 .
1/
b000000001 0
#125
0&
#126
1#
b000111111 $
b000000001 %
1&
b01110100 +
b01100110 .
0/
b000000000 0
#127
0&
#128
0#
b001000000 $
b000000000 %
1&
b10001000 +
b01101010 .
1/
b000000001 0
#129
0&
#130
1#
b001000001 $
b000000001 %
1&
b10001110 +
b01110100 .
0/
b000000000 0
#131
0&
#132
0#
b001000010 $
b000000000 %
1&
b10001000 +
b10001000 .
1/
b000000001 0
#133
0&
#134
1#
b001000011 $
b000000001 %
1&
b01101111 +
b10001110 .
0/
b000000000 0
#135
0&
#136
0#
b001000100 $
b000000000 %
1&
b01010000 +
b10001000 .
1/
b000000001 0
#137
0&
#138
1#
b001000101 $
b000000001 %
1&
b01001000 +
b01101111 .
0/
b000000000 0
#139
0&
#140
0#
b001000110 $
b000000000 %
1&
b01001001 +
b01010000 .
1/
b000000001 0
#141
0&
#142
1#
b001000111 $
b000000001 %
1&
b01001110 +
b01001000 .
0/
b000000000 0
#143
0&
#144
0#
b001001000 $
b000000000 %
1&
b01011111 +
b01001001 .
1/
b000000001 0
#145
0&
#146
1#
b001001001 $
b000000001 %
1&
b01011101 +
b01001110 .
0/
b000000000 0
#147
0&
#148
0#
b001001010 $
b000000000 %
1&
b01010100 +
b01011111 .
1/
b000000001 0
#149
0&
#150
1#
b001001011 $
b000000001 %
1&
b01010011 +
b01011101 .
0/
b000000000 0
#151
0&
#152
0#
b001001100 $
b000000000 %
1&
b01001000 +
b01010100 .
1/
b000000001 0
#153
0&
#154
1#
b001001101 $
b000000001 %
1&
b01100001 +
b01010011 .
0/
b000000000 0
#155
0&
#156
0#
b001001110 $
b000000000 %
1&
b01110110 +
b01001000 .
1/
b000000001 0
#157
0&
#158
1#
b001001111 $
b000000001 %
1&
b01111001 +
b01100001 .
0/
b000000000 0
#159
0&
#160
0#
b001010000 $
b000000000 %
1&
b01111111 +
b01110110 .
1/
b000000001 0
#161
0&
#162
1#
b001010001 $
b000000001 %
1&
b01111010 +
b01111001 .
0/
b000000000 0
#163
0&
#164
0#
b001010010 $
b000000000 %
1&
b01100001 +
b01111111 .
1/
b000000001 0
#165
0&
#166
1#
b001010011 $
b000000001 %
1&
b01011100 +
b01111010 .
0/
b000000000 0
#167
0&
#168
0#
b001010100 $
b000000000 %
1&
b01100000 +
b01100001 .
1/
b000000001 0
#169
0&
#170
1#
b001010101 $
b000000001 %
1&
b01101110 +
b01011100 .
0/
b000000000 0
#171
0&
#172
0#
b001010110 $
b000000000 %
1&
b01111010 +
b01100000 .
1/
b000000001 0
#173
0&
#174
1#
b001010111 $
b000000001 %
1&
b01101000 +
b01101110 .
0/
b000000000 0
#175
0&
#176
0#
b001011000 $
b000000000 %
1&
b01100100 +
b01111010 .
1/
b000000001 0
#177
0&
#178
1#
b001011001 $
b000000001 %
1&
b01011111 +
b01101000 .
0/
b000000000 0
#179
0&
#180
0#
b001011010 $
b000000000 %
1&
b01010111 +
b01100100 .
1/
b000000001 0
#181
0&
#182
1#
b001011011 $
b000000001 %
1&
b01011110 +
b01011111 .
0/
b000000000 0
#183
0&
#184
0#
b001011100 $
b000000000 %
1&
b01101110 +
b01010111 .
1/
b000000001 0
#185
0&
#186
1#
b001011101 $
b000000001 %
1&
b10000001 +
b01011110 .
0/
b000000000 0
#187
0&
#188
0#
b001011110 $
b000000000 %
1&
b01111010 +
b01101110 .
1/
b000000001 0
#189
0&
#190
1#
b001011111 $
b000000001 %
1&
b01101011 +
b10000001 .
0/
b000000000 0
#191
0&
#192
0#
b001100000 $
b000000000 %
1&
b01011110 +
b01111010 .
1/
b000000001 0
#193
0&
#194
1#
b001100001 $
b000000001 %
1&
b01011111 +
b01101011 .
0/
b000000000 0
#195
0&
#196
0#
b001100010 $
b000000000 %
1&
b01100001 +
b01011110 .
1/
b000000001 0
#197
0&
#198
1#
b001100011 $
b000000001 %
1&
b01101000 +
b01011111 .
0/
b000000000 0
#199
0&
#200
0#
b001100100 $
b000000000 %
1&
b01101001 +
b01100001 .
1/
b000000001 0
#201
0&
#202
1#
b001100101 $
b000000001 %
1&
b01101010 +
b01101000 .
0/
b000000000 0
#203
0&
#204
0#
b001100110 $
b000000000 %
1&
b01101001 .
1/
b000000001 0
#205
0&
#206
1#
b001100111 $
b000000001 %
1&
b01011110 +
b01101010 .
0/
b000000000 0
#207
0&
#208
0#
b001101000 $
b000000000 %
1&
b01011101 +
1/
b000000001 0
#209
0&
#210
1#
b001101001 $
b000000001 %
1&
b01100101 +
b01011110 .
0/
b000000000 0
#211
0&
#212
0#
b001101010 $
b000000000 %
1&
b01100111 +
b01011101 .
1/
b000000001 0
#213
0&
#214
1#
b001101011 $
b000000001 %
1&
b01100110 +
b01100101 .
0/
b000000000 0
#215
0&
#216
0#
b001101100 $
b000000000 %
1&
b01100010 +
b01100111 .
1/
b000000001 0
#217
0&
#218
1#
b001101101 $
b000000001 %
1&
b01100111 +
b01100110 .
0/
b000000000 0
#219
0&
#220
0#
b001101110 $
b000000000 %
1&
b01010010 +
b01100010 .
1/
b000000001 0
#221
0&
#222
1#
b001101111 $
b000000001 %
1&
b01001111 +
b01100111 .
0/
b000000000 0
#223
0&
#224
0#
b001110000 $
b000000000 %
1&
b01010101 +
b01010010 .
1/
b000000001 0
#225
0&
#226
1#
b001110001 $
b000000001 %
1&
b01100110 +
b01001111 .
0/
b000000000 0
#227
0&
#228
0#
b001110010 $
b000000000 %
1&
b10000101 +
b01010101 .
1/
b000000001 0
#229
0&
#230
1#
b001110011 $
b000000001 %
1&
b10000011 +
b01100110 .
0/
b000000000 0
#231
0&
#232
0#
b001110100 $
b000000000 %
1&
b10010011 +
b10000101 .
1/
b000000001 0
#233
0&
#234
1#
b001110101 $
b000000001 %
1&
b10001101 +
b10000011 .
0/
b000000000 0
#235
0&
#236
0#
b001110110 $
b000000000 %
1&
b01101100 +
b10010011 .
1/
b000000001 0
#237
0&
#238
1#
b001110111 $
b000000001 %
1&
b01101110 +
b10001101 .
0/
b000000000 0
#239
0&
#240
0#
b001111000 $
b000000000 %
1&
b01100011 +
b01101100 .
1/
b000000001 0
#241
0&
#242
1#
b001111001 $
b000000001 %
1&
b01011110 +
b01101110 .
0/
b000000000 0
#243
0&
#244
0#
b001111010 $
b000000000 %
1&
b01100111 +
b01100011 .
1/
b000000001 0
#245
0&
#246
1#
b001111011 $
b000000001 %
1&
b01010110 +
b01011110 .
0/
b000000000 0
#247
0&
#248
0#
b001111100 $
b000000000 %
1&
b01010101 +
b01100111 .
1/
b000000001 0
#249
0&
#250
1#
b001111101 $
b000000001 %
1&
b01011011 +
b01010110 .
0/
b000000000 0
#251
0&
#252
0#
b001111110 $
b000000000 %
1&
b01000011 +
b01010101 .
1/
b000000001 0
#253
0&
#254
1#
b001111111 $
b000000001 %
1&
b01010011 +
b01011011 .
0/
b000000000 0
#255
0&
#256
0#
b010000000 $
b000000000 %
1&
b01100100 +
b01000011 .
1/
b000000001 0
#257
0&
#258
1#
b010000001 $
b000000001 %
1&
b01011111 +
b01010011 .
0/
b000000000 0
#259
0&
#260
0#
b010000010 $
b000000000 %
1&
b01101001 +
b01100100 .
1/
b000000001 0
#261
0&
#262
1#
b010000011 $
b000000001 %
1&
b01101101 +
b01011111 .
0/
b000000000 0
#263
0&
#264
0#
b010000100 $
b000000000 %
1&
b01101111 +
b01101001 .
1/
b000000001 0
#265
0&
#266
1#
b010000101 $
b000000001 %
1&
b01101000 +
b01101101 .
0/
b000000000 0
#267
0&
#268
0#
b010000110 $
b000000000 %
1&
b01100100 +
b01101111 .
1/
b000000001 0
#269
0&
#270
1#
b010000111 $
b000000001 %
1&
b01101110 +
b01101000 .
0/
b000000000 0
#271
0&
#272
0#
b010001000 $
b000000000 %
1&
b01111000 +
b01100100 .
1/
b000000001 0
#273
0&
#274
1#
b010001001 $
b000000001 %
1&
b01111111 +
b01101110 .
0/
b000000000 0
#275
0&
#276
0#
b010001010 $
b000000000 %
1&
b10000101 +
b01111000 .
1/
b000000001 0
#277
0&
#278
1#
b010001011 $
b000000001 %
1&
b10010000 +
b01111111 .
0/
b000000000 0
#279
0&
#280
0#
b010001100 $
b000000000 %
1&
b10001010 +
b10000101 .
1/
b000000001 0
#281
0&
#282
1#
b010001101 $
b000000001 %
1&
b10000001 +
b10010000 .
0/
b000000000 0
#283
0&
#284
0#
b010001110 $
b000000000 %
1&
b01101000 +
b10001010 .
1/
b000000001 0
#285
0&
#286
1#
b010001111 $
b000000001 %
1&
b01111100 +
b10000001 .
0/
b000000000 0
#287
0&
#288
0#
b010010000 $
b000000000 %
1&
b01111011 +
b01101000 .
1/
b000000001 0
#289
0&
#290
1#
b010010001 $
b000000001 %
1&
b01101100 +
b01111100 .
0/
b000000000 0
#291
0&
#292
0#
b010010010 $
b000000000 %
1&
b01111010 +
b01111011 .
1/
b000000001 0
#293
0&
#294
1#
b010010011 $
b000000001 %
1&
b01110100 +
b01101100 .
0/
b000000000 0
#295
0&
#296
0#
b010010100 $
b000000000 %
1&
b01110010 +
b01111010 .
1/
b000000001 0
#297
0&
#298
1#
b010010101 $
b000000001 %
1&
b01100000 +
b01110100 .
0/
b000000000 0
#299
0&
#300
0#
b010010110 $
b000000000 %
1&
b01100011 +
b01110010 .
1/
b000000001 0
#301
0&
#302
1#
b010010111 $
b000000001 %
1&
b01110011 +
b01100000 .
0/
b000000000 0
#303
0&
#304
0#
b010011000 $
b000000000 %
1&
b01100011 .
1/
b000000001 0
#305
0&
#306
1#
b010011001 $
b000000001 %
1&
b01111110 +
b01110011 .
0/
b000000000 0
#307
0&
#308
0#
b010011010 $
b000000000 %
1&
b01110110 +
1/
b000000001 0
#309
0&
#310
1#
b010011011 $
b000000001 %
1&
b01111011 +
b01111110 .
0/
b000000000 0
#311
0&
#312
0#
b010011100 $
b000000000 %
1&
b01111110 +
b01110110 .
1/
b000000001 0
#313
0&
#314
1#
b010011101 $
b000000001 %
1&
b01101111 +
b01111011 .
0/
b000000000 0
#315
0&
#316
0#
b010011110 $
b000000000 %
1&
b01110001 +
b01111110 .
1/
b000000001 0
#317
0&
#318
1#
b010011111 $
b000000001 %
1&
b01111110 +
b01101111 .
0/
b000000000 0
#319
0&
#320
0#
b010100000 $
b000000000 %
1&
b01110111 +
b01110001 .
1/
b000000001 0
#321
0&
#322
1#
b010100001 $
b000000001 %
1&
b01011010 +
b01111110 .
0/
b000000000 0
#323
0&
#324
0#
b010100010 $
b000000000 %
1&
b01011101 +
b01110111 .
1/
b000000001 0
#325
0&
#326
1#
b010100011 $
b000000001 %
1&
b01011011 +
b01011010 .
0/
b000000000 0
#327
0&
#328
0#
b010100100 $
b000000000 %
1&
b01010101 +
b01011101 .
1/
b000000001 0
#329
0&
#330
1#
b010100101 $
b000000001 %
1&
b01101010 +
b01011011 .
0/
b000000000 0
#331
0&
#332
0#
b010100110 $
b000000000 %
1&
b01101011 +
b01010101 .
1/
b000000001 0
#333
0&
#334
1#
b010100111 $
b000000001 %
1&
b01101100 +
b01101010 .
0/
b000000000 0
#335
0&
#336
0#
b010101000 $
b000000000 %
1&
b01110000 +
b01101011 .
1/
b000000001 0
#337
0&
#338
1#
b010101001 $
b000000001 %
1&
b01100110 +
b01101100 .
0/
b000000000 0
#339
0&
#340
0#
b010101010 $
b000000000 %
1&
b01110000 +
b01110000 .
1/
b000000001 0
#341
0&
#342
1#
b010101011 $
b000000001 %
1&
b01111111 +
b01100110 .
0/
b000000000 0
#343
0&
#344
0#
b010101100 $
b000000000 %
1&
b01111100 +
b01110000 .
1/
b000000001 0
#345
0&
#346
1#
b010101101 $
b000000001 %
1&
b01111111 .
0/
b000000000 0
#347
0&
#348
0#
b010101110 $
b000000000 %
1&
b10000001 +
b01111100 .
1/
b000000001 0
#349
0&
#350
1#
b010101111 $
b000000001 %
1&
b01110001 +
0/
b000000000 0
#351
0&
#352
0#
b010110000 $
b000000000 %
1&
b01110100 +
b10000001 .
1/
b000000001 0
#353
0&
#354
1#
b010110001 $
b000000001 %
1&
b01110111 +
b01110001 .
0/
b000000000 0
#355
0&
#356
0#
b010110010 $
b000000000 %
1&
b01111100 +
b01110100 .
1/
b000000001 0
#357
0&
#358
1#
b010110011 $
b000000001 %
1&
b10001001 +
b01110111 .
0/
b000000000 0
#359
0&
#360
0#
b010110100 $
b000000000 %
1&
b01111100 .
1/
b000000001 0
#361
0&
#362
1#
b010110101 $
b000000001 %
1&
b10001110 +
b10001001 .
0/
b000000000 0
#363
0&
#364
0#
b010110110 $
b000000000 %
1&
b10000111 +
1/
b000000001 0
#365
0&
#366
1#
b010110111 $
b000000001 %
1&
b01111111 +
b10001110 .
0/
b000000000 0
#367
0&
#368
0#
b010111000 $
b000000000 %
1&
b10000011 +
b10000111 .
1/
b000000001 0
#369
0&
#370
1#
b010111001 $
b000000001 %
1&
b10000110 +
b01111111 .
0/
b000000000 0
#371
0&
#372
0#
b010111010 $
b000000000 %
1&
b01111110 +
b10000011 .
1/
b000000001 0
#373
0&
#374
1#
b010111011 $
b000000001 %
1&
b10000000 +
b10000110 .
0/
b000000000 0
#375
0&
#376
0#
b010111100 $
b000000000 %
1&
b01111010 +
b01111110 .
1/
b000000001 0
#377
0&
#378
1#
b010111101 $
b000000001 %
1&
b01100010 +
b10000000 .
0/
b000000000 0
#379
0&
#380
0#
b010111110 $
b000000000 %
1&
b01101100 +
b01111010 .
1/
b000000001 0
#381
0&
#382
1#
b010111111 $
b000000001 %
1&
b01100011 +
b01100010 .
0/
b000000000 0
#383
0&
#384
0#
b011000000 $
b000000000 %
1&
b01101001 +
b01101100 .
1/
b000000001 0
#385
0&
#386
1#
b011000001 $
b000000001 %
1&
b10000100 +
b01100011 .
0/
b000000000 0
#387
0&
#388
0#
b011000010 $
b000000000 %
1&
b01111100 +
b01101001 .
1/
b000000001 0
#389
0&
#390
1#
b011000011 $
b000000001 %
1&
b10010001 +
b10000100 .
0/
b000000000 0
#391
0&
#392
0#
b011000100 $
b000000000 %
1&
b10010010 +
b01111100 .
1/
b000000001 0
#393
0&
#394
1#
b011000101 $
b000000001 %
1&
b10000001 +
b10010001 .
0/
b000000000 0
#395
0&
#396
0#
b011000110 $
b000000000 %
1&
b01111001 +
b10010010 .
1/
b000000001 0
#397
0&
#398
1#
b011000111 $
b000000001 %
1&
b01110000 +
b10000001 .
0/
b000000000 0
#399
0&
#400
0#
b011001000 $
b000000000 %
1&
b01100111 +
b01111001 .
1/
b000000001 0
#401
0&
#402
1#
b011001001 $
b000000001 %
1&
b01101001 +
b01110000 .
0/
b000000000 0
#403
0&
#404
0#
b011001010 $
b000000000 %
1&
b01101011 +
b01100111 .
1/
b000000001 0
#405
0&
#406
1#
b011001011 $
b000000001 %
1&
b01011010 +
b01101001 .
0/
b000000000 0
#407
0&
#408
0#
b011001100 $
b000000000 %
1&
b01101011 +
b01101011 .
1/
b000000001 0
#409
0&
#410
1#
b011001101 $
b000000001 %
1&
b01101000 +
b01011010 .
0/
b000000000 0
#411
0&
#412
0#
b011001110 $
b000000000 %
1&
b01110101 +
b01101011 .
1/
b000000001 0
#413
0&
#414
1#
b011001111 $
b000000001 %
1&
b10100010 +
b01101000 .
0/
b000000000 0
#415
0&
#416
0#
b011010000 $
b000000000 %
1&
b10010000 +
b01110101 .
1/
b000000001 0
#417
0&
#418
1#
b011010001 $
b000000001 %
1&
b10110010 +
b10100010 .
0/
b000000000 0
#419
0&
#420
0#
b011010010 $
b000000000 %
1&
b10011110 +
b10010000 .
1/
b000000001 0
#421
0&
#422
1#
b011010011 $
b000000001 %
1&
b01110110 +
b10110010 .
0/
b000000000 0
#423
0&
#424
0#
b011010100 $
b000000000 %
1&
b01111011 +
b10011110 .
1/
b000000001 0
#425
0&
#426
1#
b011010101 $
b000000001 %
1&
b01011001 +
b01110110 .
0/
b000000000 0
#427
0&
#428
0#
b011010110 $
b000000000 %
1&
b01011101 +
b01111011 .
1/
b000000001 0
#429
0&
#430
1#
b011010111 $
b000000001 %
1&
b01100111 +
b01011001 .
0/
b000000000 0
#431
0&
#432
0#
b011011000 $
b000000000 %
1&
b01001001 +
b01011101 .
1/
b000000001 0
#433
0&
#434
1#
b011011001 $
b000000001 %
1&
b01010010 +
b01100111 .
0/
b000000000 0
#435
0&
#436
0#
b011011010 $
b000000000 %
1&
b01010101 +
b01001001 .
1/
b000000001 0
#437
0&
#438
1#
b011011011 $
b000000001 %
1&
b01001010 +
b01010010 .
0/
b000000000 0
#439
0&
#440
0#
b011011100 $
b000000000 %
1&
b01010111 +
b01010101 .
1/
b000000001 0
#441
0&
#442
1#
b011011101 $
b000000001 %
1&
b01110100 +
b01001010 .
0/
b000000000 0
#443
0&
#444
0#
b011011110 $
b000000000 %
1&
b01110110 +
b01010111 .
1/
b000000001 0
#445
0&
#446
1#
b011011111 $
b000000001 %
1&
b01111100 +
b01110100 .
0/
b000000000 0
#447
0&
#448
0#
b011100000 $
b000000000 %
1&
b10000001 +
b01110110 .
1/
b000000001 0
#449
0&
#450
1#
b011100001 $
b000000001 %
1&
b10000101 +
b01111100 .
0/
b000000000 0
#451
0&
#452
0#
b011100010 $
b000000000 %
1&
b10001000 +
b10000001 .
1/
b000000001 0
#453
0&
#454
1#
b011100011 $
b000000001 %
1&
b01110011 +
b10000101 .
0/
b000000000 0
#455
0&
#456
0#
b011100100 $
b000000000 %
1&
b01101111 +
b10001000 .
1/
b000000001 0
#457
0&
#458
1#
b011100101 $
b000000001 %
1&
b01110101 +
b01110011 .
0/
b000000000 0
#459
0&
#460
0#
b011100110 $
b000000000 %
1&
b01110001 +
b01101111 .
1/
b000000001 0
#461
0&
#462
1#
b011100111 $
b000000001 %
1&
b10000111 +
b01110101 .
0/
b000000000 0
#463
0&
#464
0#
b011101000 $
b000000000 %
1&
b01111010 +
b01110001 .
1/
b000000001 0
#465
0&
#466
1#
b011101001 $
b000000001 %
1&
b01110111 +
b10000111 .
0/
b000000000 0
#467
0&
#468
0#
b011101010 $
b000000000 %
1&
b10000001 +
b01111010 .
1/
b000000001 0
#469
0&
#470
1#
b011101011 $
b000000001 %
1&
b01011000 +
b01110111 .
0/
b000000000 0
#471
0&
#472
0#
b011101100 $
b000000000 %
1&
b01011010 +
b10000001 .
1/
b000000001 0
#473
0&
#474
1#
b011101101 $
b000000001 %
1&
b01100111 +
b01011000 .
0/
b000000000 0
#475
0&
#476
0#
b011101110 $
b000000000 %
1&
b01011010 +
b01011010 .
1/
b000000001 0
#477
0&
#478
1#
b011101111 $
b000000001 %
1&
b01110000 +
b01100111 .
0/
b000000000 0
#479
0&
#480
0#
b011110000 $
b000000000 %
1&
b01101011 +
b01011010 .
1/
b000000001 0
#481
0&
#482
1#
b011110001 $
b000000001 %
1&
b01100111 +
b01110000 .
0/
b000000000 0
#483
0&
#484
0#
b011110010 $
b000000000 %
1&
b01100100 +
b01101011 .
1/
b000000001 0
#485
0&
#486
1#
b011110011 $
b000000001 %
1&
b01100111 +
b01100111 .
0/
b000000000 0
#487
0&
#488
0#
b011110100 $
b000000000 %
1&
b01110100 +
b01100100 .
1/
b000000001 0
#489
0&
#490
1#
b011110101 $
b000000001 %
1&
b01111111 +
b01100111 .
0/
b000000000 0
#491
0&
#492
0#
b011110110 $
b000000000 %
1&
b10001111 +
b01110100 .
1/
b000000001 0
#493
0&
#494
1#
b011110111 $
b000000001 %
1&
b01110100 +
b01111111 .
0/
b000000000 0
#495
0&
#496
0#
b011111000 $
b000000000 %
1&
b01101100 +
b10001111 .
1/
b000000001 0
#497
0&
#498
1#
b011111001 $
b000000001 %
1&
b01011110 +
b01110100 .
0/
b000000000 0
#499
0&
#500
0#
b011111010 $
b000000000 %
1&
b01000010 +
b01101100 .
1/
b000000001 0
#501
0&
